{"title":"An谩lisis de datos con Tidyverse","markdown":{"yaml":{"title":"An谩lisis de datos con Tidyverse"},"headingText":"Objetivos del curso","containsRefs":false,"markdown":"\n\nLugar: **Centro de Investigaciones Biol贸gicas del Noroeste, S.C.**\n\nInstructores: [Miguel A. Tripp Valdez](https://migueltrippcv.netlify.app/)\n\n------------------------------------------------------------------------\n\n**Tidyverse** es un conjunto de paquetes dentro del ambiente R que comparten una misma filosof铆a y gram谩tica lo que facilita la organizaci贸n, transformaci贸n y visualizaci贸n de datos tabulares.\n\n::: {.callout-tip icon=\"false\"}\n\n-   Que el alumno adquiera experiencia pr谩ctica en la utilizaci贸n de herramientas de Tidyverse, dentro del ambiente R, para ordenar, transformar y visualizar datos tabulares.\n:::\n\n#### Requisitos\n\n-   Tener experiencia minima en el uso de R\n\n-   Tener computadora personal y acceso a internet\n\n## Temario del curso\n\n+-------------+----------------+-----------------------------------------------------+\n| D铆a         | Hora           | Tema                                                |\n+=============+================+=====================================================+\n| Lunes       | 10:00 - 14:00  | **Introducci贸n**                                    |\n|             |                |                                                     |\n|             |                | -   Introducci贸n a R y Tidyverse                    |\n|             |                |                                                     |\n|             |                | -   Creaci贸n y organizaci贸n de proyectos en Rstudio |\n|             |                |                                                     |\n|             |                | -   Importar y exportar datos                       |\n|             |                |                                                     |\n|             |                | -   Tibbles                                         |\n+-------------+----------------+-----------------------------------------------------+\n| Martes      | 10:00 - 14:00  | **Manipulaci贸n de datos con Dplyr**                 |\n|             |                |                                                     |\n|             |                | -   `select()`                                      |\n|             |                |                                                     |\n|             |                | -   `filter()`                                      |\n|             |                |                                                     |\n|             |                | -   `mutate()`                                      |\n|             |                |                                                     |\n|             |                | -   pipes `%>%`                                     |\n|             |                |                                                     |\n|             |                | -   Operaciones agrupadas `group_by()`              |\n|             |                |                                                     |\n|             |                | -   `summarise()`                                   |\n+-------------+----------------+-----------------------------------------------------+\n| Mi茅rcoles   | 10:00 - 14:00  | **Visualizaci贸n de datos con ggplot**               |\n|             |                |                                                     |\n|             |                | -   Gram谩tica de las gr谩ficas                       |\n|             |                |                                                     |\n|             |                | -   Geoms y aestethics                              |\n+-------------+----------------+-----------------------------------------------------+\n| Jueves      | 10::00 - 14:00 | **Visualizaci贸n de datos con ggplot**               |\n|             |                |                                                     |\n|             |                | -   Edici贸n                                         |\n|             |                |                                                     |\n|             |                | -   ggplot sin c贸digo                               |\n+-------------+----------------+-----------------------------------------------------+\n| Viernes     | 10:00 - 14:00  | **Manipulaci贸n de datos**                           |\n|             |                |                                                     |\n|             |                | -   Operaciones por columnas (`across()`)           |\n|             |                |                                                     |\n|             |                | **Reportes**                                        |\n+-------------+----------------+-----------------------------------------------------+\n\n```{r}\n#| eval: false\n#| include: false\n\n\ncountdown::countdown(1, warn_when = 10)\n```\n","srcMarkdownNoYaml":"\n\nLugar: **Centro de Investigaciones Biol贸gicas del Noroeste, S.C.**\n\nInstructores: [Miguel A. Tripp Valdez](https://migueltrippcv.netlify.app/)\n\n------------------------------------------------------------------------\n\n**Tidyverse** es un conjunto de paquetes dentro del ambiente R que comparten una misma filosof铆a y gram谩tica lo que facilita la organizaci贸n, transformaci贸n y visualizaci贸n de datos tabulares.\n\n::: {.callout-tip icon=\"false\"}\n## Objetivos del curso\n\n-   Que el alumno adquiera experiencia pr谩ctica en la utilizaci贸n de herramientas de Tidyverse, dentro del ambiente R, para ordenar, transformar y visualizar datos tabulares.\n:::\n\n#### Requisitos\n\n-   Tener experiencia minima en el uso de R\n\n-   Tener computadora personal y acceso a internet\n\n## Temario del curso\n\n+-------------+----------------+-----------------------------------------------------+\n| D铆a         | Hora           | Tema                                                |\n+=============+================+=====================================================+\n| Lunes       | 10:00 - 14:00  | **Introducci贸n**                                    |\n|             |                |                                                     |\n|             |                | -   Introducci贸n a R y Tidyverse                    |\n|             |                |                                                     |\n|             |                | -   Creaci贸n y organizaci贸n de proyectos en Rstudio |\n|             |                |                                                     |\n|             |                | -   Importar y exportar datos                       |\n|             |                |                                                     |\n|             |                | -   Tibbles                                         |\n+-------------+----------------+-----------------------------------------------------+\n| Martes      | 10:00 - 14:00  | **Manipulaci贸n de datos con Dplyr**                 |\n|             |                |                                                     |\n|             |                | -   `select()`                                      |\n|             |                |                                                     |\n|             |                | -   `filter()`                                      |\n|             |                |                                                     |\n|             |                | -   `mutate()`                                      |\n|             |                |                                                     |\n|             |                | -   pipes `%>%`                                     |\n|             |                |                                                     |\n|             |                | -   Operaciones agrupadas `group_by()`              |\n|             |                |                                                     |\n|             |                | -   `summarise()`                                   |\n+-------------+----------------+-----------------------------------------------------+\n| Mi茅rcoles   | 10:00 - 14:00  | **Visualizaci贸n de datos con ggplot**               |\n|             |                |                                                     |\n|             |                | -   Gram谩tica de las gr谩ficas                       |\n|             |                |                                                     |\n|             |                | -   Geoms y aestethics                              |\n+-------------+----------------+-----------------------------------------------------+\n| Jueves      | 10::00 - 14:00 | **Visualizaci贸n de datos con ggplot**               |\n|             |                |                                                     |\n|             |                | -   Edici贸n                                         |\n|             |                |                                                     |\n|             |                | -   ggplot sin c贸digo                               |\n+-------------+----------------+-----------------------------------------------------+\n| Viernes     | 10:00 - 14:00  | **Manipulaci贸n de datos**                           |\n|             |                |                                                     |\n|             |                | -   Operaciones por columnas (`across()`)           |\n|             |                |                                                     |\n|             |                | **Reportes**                                        |\n+-------------+----------------+-----------------------------------------------------+\n\n```{r}\n#| eval: false\n#| include: false\n\n\ncountdown::countdown(1, warn_when = 10)\n```\n"},"formats":{"html":{"identifier":{"display-name":"HTML","target-format":"html","base-format":"html"},"execute":{"fig-width":7,"fig-height":5,"fig-format":"retina","fig-dpi":96,"df-print":"default","error":false,"eval":true,"cache":null,"freeze":false,"echo":true,"output":true,"warning":true,"include":true,"keep-md":false,"keep-ipynb":false,"ipynb":null,"enabled":null,"daemon":null,"daemon-restart":false,"debug":false,"ipynb-filters":[],"ipynb-shell-interactivity":null,"plotly-connected":true,"engine":"knitr"},"render":{"keep-tex":false,"keep-typ":false,"keep-source":false,"keep-hidden":false,"prefer-html":false,"output-divs":true,"output-ext":"html","fig-align":"default","fig-pos":null,"fig-env":null,"code-fold":"none","code-overflow":"scroll","code-link":false,"code-line-numbers":false,"code-tools":false,"tbl-colwidths":"auto","merge-includes":true,"inline-includes":false,"preserve-yaml":false,"latex-auto-mk":true,"latex-auto-install":true,"latex-clean":true,"latex-min-runs":1,"latex-max-runs":10,"latex-makeindex":"makeindex","latex-makeindex-opts":[],"latex-tlmgr-opts":[],"latex-input-paths":[],"latex-output-dir":null,"link-external-icon":false,"link-external-newwindow":false,"self-contained-math":false,"format-resources":[],"notebook-links":true},"pandoc":{"standalone":true,"wrap":"none","default-image-extension":"png","to":"html","filters":["custom-callout"],"css":["styles.css"],"toc":true,"number-sections":false,"output-file":"index.html"},"language":{"toc-title-document":"Table of contents","toc-title-website":"On this page","related-formats-title":"Other Formats","related-notebooks-title":"Notebooks","source-notebooks-prefix":"Source","other-links-title":"Other Links","code-links-title":"Code Links","launch-dev-container-title":"Launch Dev Container","launch-binder-title":"Launch Binder","article-notebook-label":"Article Notebook","notebook-preview-download":"Download Notebook","notebook-preview-download-src":"Download Source","notebook-preview-back":"Back to Article","manuscript-meca-bundle":"MECA Bundle","section-title-abstract":"Abstract","section-title-appendices":"Appendices","section-title-footnotes":"Footnotes","section-title-references":"References","section-title-reuse":"Reuse","section-title-copyright":"Copyright","section-title-citation":"Citation","appendix-attribution-cite-as":"For attribution, please cite this work as:","appendix-attribution-bibtex":"BibTeX citation:","appendix-view-license":"View License","title-block-author-single":"Author","title-block-author-plural":"Authors","title-block-affiliation-single":"Affiliation","title-block-affiliation-plural":"Affiliations","title-block-published":"Published","title-block-modified":"Modified","title-block-keywords":"Keywords","callout-tip-title":"Tip","callout-note-title":"Note","callout-warning-title":"Warning","callout-important-title":"Important","callout-caution-title":"Caution","code-summary":"Code","code-tools-menu-caption":"Code","code-tools-show-all-code":"Show All Code","code-tools-hide-all-code":"Hide All Code","code-tools-view-source":"View Source","code-tools-source-code":"Source Code","tools-share":"Share","tools-download":"Download","code-line":"Line","code-lines":"Lines","copy-button-tooltip":"Copy to Clipboard","copy-button-tooltip-success":"Copied!","repo-action-links-edit":"Edit this page","repo-action-links-source":"View source","repo-action-links-issue":"Report an issue","back-to-top":"Back to top","search-no-results-text":"No results","search-matching-documents-text":"matching documents","search-copy-link-title":"Copy link to search","search-hide-matches-text":"Hide additional matches","search-more-match-text":"more match in this document","search-more-matches-text":"more matches in this document","search-clear-button-title":"Clear","search-text-placeholder":"","search-detached-cancel-button-title":"Cancel","search-submit-button-title":"Submit","search-label":"Search","toggle-section":"Toggle section","toggle-sidebar":"Toggle sidebar navigation","toggle-dark-mode":"Toggle dark mode","toggle-reader-mode":"Toggle reader mode","toggle-navigation":"Toggle navigation","crossref-fig-title":"Figure","crossref-tbl-title":"Table","crossref-lst-title":"Listing","crossref-thm-title":"Theorem","crossref-lem-title":"Lemma","crossref-cor-title":"Corollary","crossref-prp-title":"Proposition","crossref-cnj-title":"Conjecture","crossref-def-title":"Definition","crossref-exm-title":"Example","crossref-exr-title":"Exercise","crossref-ch-prefix":"Chapter","crossref-apx-prefix":"Appendix","crossref-sec-prefix":"Section","crossref-eq-prefix":"Equation","crossref-lof-title":"List of Figures","crossref-lot-title":"List of Tables","crossref-lol-title":"List of Listings","environment-proof-title":"Proof","environment-remark-title":"Remark","environment-solution-title":"Solution","listing-page-order-by":"Order By","listing-page-order-by-default":"Default","listing-page-order-by-date-asc":"Oldest","listing-page-order-by-date-desc":"Newest","listing-page-order-by-number-desc":"High to Low","listing-page-order-by-number-asc":"Low to High","listing-page-field-date":"Date","listing-page-field-title":"Title","listing-page-field-description":"Description","listing-page-field-author":"Author","listing-page-field-filename":"File Name","listing-page-field-filemodified":"Modified","listing-page-field-subtitle":"Subtitle","listing-page-field-readingtime":"Reading Time","listing-page-field-wordcount":"Word Count","listing-page-field-categories":"Categories","listing-page-minutes-compact":"{0} min","listing-page-category-all":"All","listing-page-no-matches":"No matching items","listing-page-words":"{0} words","listing-page-filter":"Filter","draft":"Draft"},"metadata":{"lang":"en","fig-responsive":true,"quarto-version":"1.5.53","editor":"visual","custom-callout":{"ejercicio":{"icon-symbol":"fa-thumbs-up","title":"Ejercicio","color":"#f56c49","appearance":"default"},"todo":{"icon-symbol":"","color":"pink"},"thumbs-up":{"title":"Great job!","icon-symbol":"fa-thumbs-up","color":"#008000"}},"grid":{"body-width":"1200px","margin-width":"200px","sidebar-width":"220px"},"theme":{"light":"flatly","dark":"darkly"},"toc-title":"Contenido","toc-expand":1,"toc-location":"left","page-layout":"article","title":"An谩lisis de datos con Tidyverse"},"extensions":{"book":{"multiFile":true}}}},"projectFormats":["html"]}